just_heic/__init__.py
just_heic/change_date.py
just_heic/heic_to_jpg.py
just_heic/main.py
just_heic/utils.py
just_heic/__pycache__/__init__.cpython-311.pyc
just_heic/__pycache__/change_date.cpython-311.pyc
just_heic/__pycache__/heic_to_jpg.cpython-311.pyc
just_heic/__pycache__/main.cpython-311.pyc
just_heic/__pycache__/utils.cpython-311.pyc
just_heic-0.0.0.dist-info/LICENSE
just_heic-0.0.0.dist-info/METADATA
just_heic-0.0.0.dist-info/WHEEL
just_heic-0.0.0.dist-info/entry_points.txt
just_heic-0.0.0.dist-info/top_level.txt
just_heic-0.0.0.dist-info/RECORD
